AUTHORS
CHANGES
COPYING
INSTALL
MANIFEST.in
README
setup.cfg
setup.py
src/quantclient/__init__.py
src/quantclient/apiclient.py
src/quantclient/test.py
src/quantclient.egg-info/PKG-INFO
src/quantclient.egg-info/SOURCES.txt
src/quantclient.egg-info/dependency_links.txt
src/quantclient.egg-info/not-zip-safe
src/quantclient.egg-info/requires.txt
src/quantclient.egg-info/top_level.txt